odoo/addons/stock_picking_tier_validation/README.rst
odoo/addons/stock_picking_tier_validation/__init__.py
odoo/addons/stock_picking_tier_validation/__manifest__.py
odoo/addons/stock_picking_tier_validation/i18n/stock_picking_tier_validation.pot
odoo/addons/stock_picking_tier_validation/models/__init__.py
odoo/addons/stock_picking_tier_validation/models/stock_picking.py
odoo/addons/stock_picking_tier_validation/models/tier_definition.py
odoo/addons/stock_picking_tier_validation/readme/CONFIGURE.rst
odoo/addons/stock_picking_tier_validation/readme/CONTRIBUTORS.rst
odoo/addons/stock_picking_tier_validation/readme/DESCRIPTION.rst
odoo/addons/stock_picking_tier_validation/readme/INSTALL.rst
odoo/addons/stock_picking_tier_validation/readme/USAGE.rst
odoo/addons/stock_picking_tier_validation/static/description/icon.png
odoo/addons/stock_picking_tier_validation/static/description/index.html
odoo/addons/stock_picking_tier_validation/tests/__init__.py
odoo/addons/stock_picking_tier_validation/tests/common.py
odoo/addons/stock_picking_tier_validation/tests/test_tier_validation.py
odoo/addons/stock_picking_tier_validation/tests/tier_validation_tester.py
odoo/addons/stock_picking_tier_validation/views/stock_picking_views.xml
odoo12_addon_stock_picking_tier_validation-12.0.1.0.1.dist-info/METADATA
odoo12_addon_stock_picking_tier_validation-12.0.1.0.1.dist-info/WHEEL
odoo12_addon_stock_picking_tier_validation-12.0.1.0.1.dist-info/top_level.txt
odoo12_addon_stock_picking_tier_validation-12.0.1.0.1.dist-info/RECORD
