Metadata-Version: 2.1
Name: odoo12-addon-stock-picking-tier-validation
Version: 12.0.1.0.1
Summary: Extends the functionality of Transfers to support a tier validation process.
Home-page: https://github.com/OCA/stock-logistics-workflow
Author: Ecosoft, Odoo Community Association (OCA)
Author-email: support@odoo-community.org
License: AGPL-3
Platform: UNKNOWN
Classifier: Programming Language :: Python
Classifier: Framework :: Odoo
Classifier: Framework :: Odoo :: 12.0
Classifier: License :: OSI Approved :: GNU Affero General Public License v3
Classifier: Development Status :: 3 - Alpha
Requires-Python: >=3.5
Requires-Dist: odoo12-addon-base-tier-validation
Requires-Dist: odoo (<12.1dev,>=12.0a)
